{
  "zoxide/macos/arm64": {
    "version": "0.9.7",
    "updated_at": "2025-03-11T09:09:22.638474"
  },
  "zoxide/linux/arm64": {
    "version": "0.9.7",
    "updated_at": "2025-03-11T09:09:22.660703"
  },
  "zoxide/linux/amd64": {
    "version": "0.9.7",
    "updated_at": "2025-03-11T09:09:22.680178"
  },
  "uv/macos/arm64": {
    "version": "0.6.6",
    "updated_at": "2025-03-15T22:31:12.557111",
    "sha256": "d0fb047593122746c7529960f8efd5d7d10d2cb230302f71158e9765ad37727b"
  },
  "ripgrep/linux/arm64": {
    "version": "14.1.1",
    "updated_at": "2025-03-11T09:09:22.803508"
  },
  "ripgrep/linux/amd64": {
    "version": "14.1.1",
    "updated_at": "2025-03-11T09:09:22.831274"
  },
  "ripgrep/macos/arm64": {
    "version": "14.1.1",
    "updated_at": "2025-03-11T09:09:22.853795"
  },
  "uv/linux/arm64": {
    "version": "0.6.6",
    "updated_at": "2025-03-15T22:31:11.525638",
    "sha256": "37a543598cdb7d8fc9b74e6b1fe1fdf8b9a279c6137c7ff8396a88f69ec7a43c"
  },
  "uv/linux/amd64": {
    "version": "0.6.6",
    "updated_at": "2025-03-15T22:31:12.451712",
    "sha256": "4c3426c4919d9f44633ab9884827fa1ad64ad8d993516d636eb955a3835c4a8c"
  },
  "delta/macos/arm64": {
    "version": "0.18.2",
    "updated_at": "2025-03-11T09:09:23.081204"
  },
  "delta/linux/arm64": {
    "version": "0.18.2",
    "updated_at": "2025-03-11T09:09:23.103454"
  },
  "delta/linux/amd64": {
    "version": "0.18.2",
    "updated_at": "2025-03-11T09:09:23.127046"
  },
  "eza/linux/arm64": {
    "version": "0.20.24",
    "updated_at": "2025-03-15T22:31:11.009724",
    "sha256": "e3083f294a8be8dbd875dbaf77522420257e9bc6fad743c9103a95ff34be86ec"
  },
  "atuin/macos/arm64": {
    "version": "18.4.0",
    "updated_at": "2025-03-11T09:09:23.210960"
  },
  "eza/linux/amd64": {
    "version": "0.20.24",
    "updated_at": "2025-03-15T22:31:10.994773",
    "sha256": "8652aebadce970e0b4208c7181c12eb14ffc62f56717d4c9fb4aac1958b1ea0c"
  },
  "atuin/linux/arm64": {
    "version": "18.4.0",
    "updated_at": "2025-03-11T09:09:23.311052"
  },
  "atuin/linux/amd64": {
    "version": "18.4.0",
    "updated_at": "2025-03-11T09:09:23.399370"
  },
  "git-lfs/macos/arm64": {
    "version": "3.6.1",
    "updated_at": "2025-03-11T09:09:23.468256"
  },
  "git-lfs/linux/amd64": {
    "version": "3.6.1",
    "updated_at": "2025-03-11T09:09:23.545007"
  },
  "fzf/linux/amd64": {
    "version": "0.60.3",
    "updated_at": "2025-03-11T09:09:23.558546"
  },
  "fzf/macos/arm64": {
    "version": "0.60.3",
    "updated_at": "2025-03-11T09:09:23.572836"
  },
  "fzf/linux/arm64": {
    "version": "0.60.3",
    "updated_at": "2025-03-11T09:09:23.585925"
  },
  "git-lfs/linux/arm64": {
    "version": "3.6.1",
    "updated_at": "2025-03-11T09:09:23.662873"
  },
  "micromamba/linux/arm64": {
    "version": "2.0.7-0",
    "updated_at": "2025-03-15T22:31:11.997506",
    "sha256": "543079535922bf84e447f67f23c3ea6f54b2d84dd8e58ace99b47cfe6aa06ec6"
  },
  "micromamba/linux/amd64": {
    "version": "2.0.7-0",
    "updated_at": "2025-03-15T22:31:11.378537",
    "sha256": "e181494d8932a0dc6ab0fe38dab6dacce9b814f72f74986f7037f94402116940"
  },
  "micromamba/macos/arm64": {
    "version": "2.0.7-0",
    "updated_at": "2025-03-15T22:31:12.332699",
    "sha256": "ff820151dfe9d7cff31ce40942b4ef946a747ed1274427d6211a0099bed8913e"
  },
  "bat/macos/arm64": {
    "version": "0.25.0",
    "updated_at": "2025-03-11T09:09:25.822031"
  },
  "bat/linux/arm64": {
    "version": "0.25.0",
    "updated_at": "2025-03-11T09:09:25.847020"
  },
  "bat/linux/amd64": {
    "version": "0.25.0",
    "updated_at": "2025-03-11T09:09:25.873916"
  },
  "eget/macos/arm64": {
    "version": "1.3.4",
    "updated_at": "2025-03-15T22:31:11.401487",
    "sha256": "47398a317d75b0eae103a9ff9be86729295f659b3ab9bbe2cabc7c48ef35a0c6"
  },
  "eget/linux/amd64": {
    "version": "1.3.4",
    "updated_at": "2025-03-15T22:31:11.423584",
    "sha256": "c6b3da99e494e14a9f8c2877f9eb5891d573a95f436ecba7013cfb7d0992abf5"
  },
  "eget/linux/arm64": {
    "version": "1.3.4",
    "updated_at": "2025-03-15T22:31:11.549547",
    "sha256": "2258d8e52a1906e5ac5c32d940b5ff2807ab93873827e4cbe9e959f5ebf16188"
  }
}